<?xml version="1.0" encoding="UTF-8"?>
<plugins>
  <pyqgis_plugin name="EditorMetadadosSNIMar" version="{{ plugin_version }}">
    <description><![CDATA[Plugin para criação e edição de metadados segundo o perfil SNIMar]]></description>
    <about><![CDATA[O Editor de Metadados SNIMar foi desenvolvido no âmbito do Projeto SNIMar com o objetivo de ser a ferramenta destinada à criação dos metadados em conformidade com o Perfil de Metadados SNIMar.]]></about>
    <version>{{ plugin_version }}</version>
    <qgis_minimum_version>3.0.0</qgis_minimum_version>
    <homepage>http://editor.snimar.pt/</homepage>
    <file_name>{{ plugin_filename }}</file_name>
    <icon>../main_icon.png</icon>
    <author_name><![CDATA[Main Developers: Pedro Dias, Eduardo Castanho;
      Contributors: Joana Teixeira, Alexandre Neto]]></author_name>
    <download_url>{{ plugin_download_url }}</download_url>
    <uploaded_by><![CDATA[Team WP4-SNIMar]]></uploaded_by>
    <create_date>2015-08-10T12:07:15.672750</create_date>
    <update_date>{{ plugin_update_date }}</update_date>
    <tags><![CDATA[Metadata,Metadados,SNIMar,EEAgrants,Governo Portugal]]></tags>
    <experimental>False</experimental>
  </pyqgis_plugin>
</plugins>
